rongcloud_server_mcp/__init__.py
rongcloud_server_mcp/__main__.py
rongcloud_server_mcp/server.py
rongcloud_server_mcp/version.py
rongcloud_server_mcp/sdk/__init__.py
rongcloud_server_mcp/sdk/base_client.py
rongcloud_server_mcp/sdk/client.py
rongcloud_server_mcp/sdk/exceptions.py
rongcloud_server_mcp/sdk/services/__init__.py
rongcloud_server_mcp/sdk/services/group.py
rongcloud_server_mcp/sdk/services/message.py
rongcloud_server_mcp/sdk/services/user.py
rongcloud_server_mcp_python-0.1.0.dist-info/METADATA
rongcloud_server_mcp_python-0.1.0.dist-info/WHEEL
rongcloud_server_mcp_python-0.1.0.dist-info/entry_points.txt
rongcloud_server_mcp_python-0.1.0.dist-info/licenses/LICENSE
rongcloud_server_mcp_python-0.1.0.dist-info/RECORD
