Metadata-Version: 2.4
Name: rongcloud-server-mcp-python
Version: 0.1.0
Summary: An MCP server implementation based on RongCloud IM Server.
Project-URL: Home, https://github.com/rongcloud/rcloud-server-mcp-python
Project-URL: Source, https://github.com/rongcloud/rcloud-server-mcp-python.git
Project-URL: Changelog, https://github.com/rongcloud/rcloud-server-mcp-python/CHANGELOG.md
License-Expression: MIT
License-File: LICENSE
Requires-Python: >=3.12
Requires-Dist: httpx>=0.28.1
Requires-Dist: loguru>=0.7.0
Requires-Dist: mcp[cli]>=1.9.1
Requires-Dist: pydantic>=2.10.6
Provides-Extra: dev
Requires-Dist: pytest-asyncio>=0.26.0; extra == 'dev'
Requires-Dist: pytest-cov>=4.1.0; extra == 'dev'
Requires-Dist: pytest-mock>=3.11.1; extra == 'dev'
Requires-Dist: pytest>=7.4.0; extra == 'dev'
Requires-Dist: ruff>=0.9.7; extra == 'dev'
